iriusrisk_cli/__init__.py
iriusrisk_cli/api_client.py
iriusrisk_cli/cli_context.py
iriusrisk_cli/config.py
iriusrisk_cli/container.py
iriusrisk_cli/exceptions.py
iriusrisk_cli/main.py
iriusrisk_cli/service_factory.py
iriusrisk_cli/api/__init__.py
iriusrisk_cli/api/base_client.py
iriusrisk_cli/api/countermeasure_client.py
iriusrisk_cli/api/health_client.py
iriusrisk_cli/api/project_client.py
iriusrisk_cli/api/questionnaire_client.py
iriusrisk_cli/api/report_client.py
iriusrisk_cli/api/threat_client.py
iriusrisk_cli/api/version_client.py
iriusrisk_cli/commands/__init__.py
iriusrisk_cli/commands/components.py
iriusrisk_cli/commands/config_cmd.py
iriusrisk_cli/commands/countermeasures.py
iriusrisk_cli/commands/init.py
iriusrisk_cli/commands/issue_trackers.py
iriusrisk_cli/commands/mcp.py
iriusrisk_cli/commands/otm.py
iriusrisk_cli/commands/projects.py
iriusrisk_cli/commands/reports.py
iriusrisk_cli/commands/sync.py
iriusrisk_cli/commands/threats.py
iriusrisk_cli/commands/updates.py
iriusrisk_cli/commands/versions.py
iriusrisk_cli/prompts/analyze_source_material.md
iriusrisk_cli/prompts/architecture_and_design_review.md
iriusrisk_cli/prompts/create_threat_model.md
iriusrisk_cli/prompts/initialize_iriusrisk_workflow.md
iriusrisk_cli/prompts/questionnaire_guidance.md
iriusrisk_cli/prompts/security_development_advisor.md
iriusrisk_cli/prompts/threats_and_countermeasures.md
iriusrisk_cli/repositories/__init__.py
iriusrisk_cli/repositories/base_repository.py
iriusrisk_cli/repositories/countermeasure_repository.py
iriusrisk_cli/repositories/project_repository.py
iriusrisk_cli/repositories/questionnaire_repository.py
iriusrisk_cli/repositories/report_repository.py
iriusrisk_cli/repositories/threat_repository.py
iriusrisk_cli/repositories/version_repository.py
iriusrisk_cli/services/__init__.py
iriusrisk_cli/services/countermeasure_service.py
iriusrisk_cli/services/health_service.py
iriusrisk_cli/services/project_service.py
iriusrisk_cli/services/questionnaire_service.py
iriusrisk_cli-0.4.0.dist-info/licenses/LICENSE
iriusrisk_cli-0.4.0.dist-info/METADATA
iriusrisk_cli-0.4.0.dist-info/WHEEL
iriusrisk_cli-0.4.0.dist-info/entry_points.txt
iriusrisk_cli-0.4.0.dist-info/top_level.txt
iriusrisk_cli-0.4.0.dist-info/RECORD
