Metadata-Version: 2.4
Name: iriusrisk-cli
Version: 0.4.0
Summary: AI-powered threat modeling integration for IriusRisk. Command line interface and MCP server for security analysis.
Home-page: https://github.com/iriusrisk/iriusrisk_cli
Author: IriusRisk
Author-email: support@iriusrisk.com
Project-URL: Bug Reports, https://github.com/iriusrisk/iriusrisk_cli/issues
Project-URL: Documentation, https://github.com/iriusrisk/iriusrisk_cli#readme
Project-URL: Source, https://github.com/iriusrisk/iriusrisk_cli
Project-URL: Changelog, https://github.com/iriusrisk/iriusrisk_cli/blob/main/CHANGELOG.md
Keywords: security,threat-modeling,iriusrisk,cli,mcp,ai,threat-analysis,security-testing,compliance,cybersecurity
Classifier: Development Status :: 3 - Alpha
Classifier: Intended Audience :: Developers
Classifier: Intended Audience :: Information Technology
Classifier: Intended Audience :: System Administrators
Classifier: License :: OSI Approved :: MIT License
Classifier: Operating System :: OS Independent
Classifier: Programming Language :: Python :: 3
Classifier: Programming Language :: Python :: 3.8
Classifier: Programming Language :: Python :: 3.9
Classifier: Programming Language :: Python :: 3.10
Classifier: Programming Language :: Python :: 3.11
Classifier: Programming Language :: Python :: 3.12
Classifier: Topic :: Security
Classifier: Topic :: Software Development :: Quality Assurance
Classifier: Topic :: Software Development :: Testing
Classifier: Environment :: Console
Requires-Python: >=3.8
License-File: LICENSE
Requires-Dist: click>=8.0.0
Requires-Dist: requests>=2.25.0
Requires-Dist: python-dotenv>=0.19.0
Requires-Dist: tabulate>=0.8.0
Requires-Dist: mcp>=1.0.0
Dynamic: author
Dynamic: author-email
Dynamic: classifier
Dynamic: description
Dynamic: description-content-type
Dynamic: home-page
Dynamic: keywords
Dynamic: license-file
Dynamic: project-url
Dynamic: requires-dist
Dynamic: requires-python
Dynamic: summary
